Calci/__init__.py
Clci-0.1.dist-info/LICENSE.txt
Clci-0.1.dist-info/METADATA
Clci-0.1.dist-info/WHEEL
Clci-0.1.dist-info/top_level.txt
Clci-0.1.dist-info/RECORD
