Metadata-Version: 2.1
Name: Clci
Version: 0.1
Summary: simple calci
Home-page: UNKNOWN
Author: bhavani
Author-email: durgabhavani1622@gmail.com
License: UNKNOWN
Platform: UNKNOWN
Classifier: Programming Language :: Python :: 3
Classifier: License :: OSI Approved :: MIT License
Classifier: Operating System :: OS Independent
